<Defs xmlns:xsi="http://www.w3.org/2001/XMLSchema-instance" xsi:noNamespaceSchemaLocation="../../Schemas/ThoughtDef.xsd">
	<ThoughtDef ParentName="OutlookMemoryBase">
        <durationDays>1</durationDays>
        <defName>EtherKuluBeak</defName>
        <stages>
            <li>
                <label>Kulu beak</label>
                <description>I look like a dodo. Can't talk well either.</description>
                <visible>true</visible>
                <baseMoodEffect>-1</baseMoodEffect>
            </li>
            <li>
                <label>Kulu face</label>
                <description>Squawk!</description>
                <visible>true</visible>
                <baseMoodEffect>3</baseMoodEffect>
            </li>
            <li>
                <label>Kulu face</label>
                <description>My face!</description>
                <visible>true</visible>
                <baseMoodEffect>-3</baseMoodEffect>
            </li>
        </stages>
		</ThoughtDef>
		<ThoughtDef ParentName="OutlookMemoryBase">
        <durationDays>1</durationDays>
        <defName>EtherKuluPlume</defName>
        <stages>
            <li>
                <label>Kulu plume</label>
                <description>Fancy feathers eh?</description>
                <visible>true</visible>
                <baseMoodEffect>-1</baseMoodEffect>
            </li>
            <li>
                <label>Kulu plume</label>
                <description>So colorful. I love it!</description>
                <visible>true</visible>
                <baseMoodEffect>2</baseMoodEffect>
            </li>
            <li>
                <label>Kulu plume</label>
                <description>Feathers? I dont want to be a bird!</description>
                <visible>true</visible>
                <baseMoodEffect>-2</baseMoodEffect>
            </li>
        </stages>
    </ThoughtDef>
    <ThoughtDef ParentName="OutlookMemoryBase">
        <durationDays>1</durationDays>
        <defName>EtherKuluTail</defName>
        <stages>
            <li>
                <label>Kulu tail</label>
                <description>I keep bumping into stuff with it.</description>
                <visible>true</visible>
                <baseMoodEffect>-1</baseMoodEffect>
            </li>
            <li>
                <label>Kulu tail</label>
                <description>It helps with my balance a lot. I really like that pattern too.</description>
                <visible>true</visible>
                <baseMoodEffect>3</baseMoodEffect>
            </li>
            <li>
                <label>Kulu tail</label>
                <description>Gah! Stupid tail!</description>
                <visible>true</visible>
                <baseMoodEffect>-3</baseMoodEffect>
            </li>
        </stages>
    </ThoughtDef>
</Defs>